{"title":"[CollegeRules] Tag-Team These College-Girls (cr12139 / 08.08.201","uid":8793699,"size":442949891,"categoryP":"porn","categoryS":"movies","magnet":"?xt=urn:btih:01911ad5625d3b7caa4757794f93a99a5a9a37b6&amp;dn=%5BCollegeRules%5D+Tag-Team+These+College-Girls+%28cr12139+%2F+08.08.201&amp;tr=udp%3A%2F%2Ftracker.openbittorrent.com%3A80&amp;tr=udp%3A%2F%2Fopen.demonii.com%3A1337&amp;tr=udp%3A%2F%2Ftracker.coppersurfer.tk%3A6969&amp;tr=udp%3A%2F%2Fexodus.desync.com%3A6969","seeders":1,"leechers":0,"uploader":"chkm8te","files":2,"time":1376017606,"description":"[CollegeRules] Tag-Team These College-Girls (cr12139 / 08.08.2013)\n\nScreens: &lt;a href=&quot;\nhttp://xxxhost.me/viewer.php?file=hqnvh90ary1uom8mwsxe.jpg&quot; rel=&quot;nofollow&quot; target=&quot;_NEW&quot;&gt;\nhttp://xxxhost.me/viewer.php?file=hqnvh90ary1uom8mwsxe.jpg&lt;/a&gt;\n &lt;a href=&quot;\nhttp://xxxhost.me/viewer.php?file=5kt5mufqytj1303uqirx.jpg&quot; rel=&quot;nofollow&quot; target=&quot;_NEW&quot;&gt;\nhttp://xxxhost.me/viewer.php?file=5kt5mufqytj1303uqirx.jpg&lt;/a&gt;","torrent":{"xt":"urn:btih:01911ad5625d3b7caa4757794f93a99a5a9a37b6","amp;dn":"%5BCollegeRules%5D+Tag-Team+These+College-Girls+%28cr12139+%2F+08.08.201","amp;tr":["udp%3A%2F%2Ftracker.openbittorrent.com%3A80","udp%3A%2F%2Fopen.demonii.com%3A1337","udp%3A%2F%2Ftracker.coppersurfer.tk%3A6969","udp%3A%2F%2Fexodus.desync.com%3A6969"],"infoHash":"01911ad5625d3b7caa4757794f93a99a5a9a37b6","infoHashBuffer":{"type":"Buffer","data":[1,145,26,213,98,93,59,124,170,71,87,121,79,147,169,154,90,154,55,182]},"announce":[],"urlList":[]}}