{"title":"Australian Open.2014.F.W.D.(24 jan).Erani/Vinci-Makarova/Vesnina","uid":9518684,"size":2692255720,"categoryP":"video","categoryS":"tv_shows","magnet":"?xt=urn:btih:06680bbab44c58601dbe7aee684f2c841999cc70&amp;dn=Australian+Open.2014.F.W.D.%2824+jan%29.Erani%2FVinci-Makarova%2FVesnina&amp;tr=udp%3A%2F%2Ftracker.openbittorrent.com%3A80&amp;tr=udp%3A%2F%2Fopen.demonii.com%3A1337&amp;tr=udp%3A%2F%2Ftracker.coppersurfer.tk%3A6969&amp;tr=udp%3A%2F%2Fexodus.desync.com%3A6969","seeders":1,"leechers":0,"uploader":"Nepotu","files":1,"time":1390586112,"description":"AUSTRALIAN OPEN 2014 - 24 january - Final - Women doubles\n\n\nSara Errani (ITA, 1)/Roberta Vinci (ITA, 1) - Ekaterina Makarova (RUS, 3)/Elena Vesnina (RUS, 3)\n\n\n\n\n\nCredit: Bagga\t","torrent":{"xt":"urn:btih:06680bbab44c58601dbe7aee684f2c841999cc70","amp;dn":"Australian+Open.2014.F.W.D.%2824+jan%29.Erani%2FVinci-Makarova%2FVesnina","amp;tr":["udp%3A%2F%2Ftracker.openbittorrent.com%3A80","udp%3A%2F%2Fopen.demonii.com%3A1337","udp%3A%2F%2Ftracker.coppersurfer.tk%3A6969","udp%3A%2F%2Fexodus.desync.com%3A6969"],"infoHash":"06680bbab44c58601dbe7aee684f2c841999cc70","infoHashBuffer":{"type":"Buffer","data":[6,104,11,186,180,76,88,96,29,190,122,238,104,79,44,132,25,153,204,112]},"announce":[],"urlList":[]}}