{"title":"Celldweller Soundtrack for the Voices in My Head: Volume 03","uid":8679773,"size":22730111,"categoryP":"audio","categoryS":"music","magnet":"?xt=urn:btih:1400f062f082483c3ade8717773f393a5909714a&amp;dn=Celldweller+Soundtrack+for+the+Voices+in+My+Head%3A+Volume+03&amp;tr=udp%3A%2F%2Ftracker.openbittorrent.com%3A80&amp;tr=udp%3A%2F%2Fopen.demonii.com%3A1337&amp;tr=udp%3A%2F%2Ftracker.coppersurfer.tk%3A6969&amp;tr=udp%3A%2F%2Fexodus.desync.com%3A6969","seeders":1,"leechers":0,"uploader":"ukenceto","files":-1,"time":1373667639,"description":"Soundtrack for the Voices in My Head: Volume 03 is the third production-based (fifth overall) album by the American electronic rock artist, Celldweller. It is the third album in the Soundtrack for the Voices in My Head series.\n\nGenre: Electronic rock, Ambient, Dub step\nCountry: USA\nYear: 2013\nAudio codec: MP3\nRip: tracks\nBit rate: 320 kbps\n\nTracklist:\n1. Razorface (3:14)\n2. Hyperion (2:26)\n3. Battlecry (1:24)\n4. Jupiter (2:14) ","torrent":{"xt":"urn:btih:1400f062f082483c3ade8717773f393a5909714a","amp;dn":"Celldweller+Soundtrack+for+the+Voices+in+My+Head%3A+Volume+03","amp;tr":["udp%3A%2F%2Ftracker.openbittorrent.com%3A80","udp%3A%2F%2Fopen.demonii.com%3A1337","udp%3A%2F%2Ftracker.coppersurfer.tk%3A6969","udp%3A%2F%2Fexodus.desync.com%3A6969"],"infoHash":"1400f062f082483c3ade8717773f393a5909714a","infoHashBuffer":{"type":"Buffer","data":[20,0,240,98,240,130,72,60,58,222,135,23,119,63,57,58,89,9,113,74]},"announce":[],"urlList":[]}}