{"title":"A Taste Of Two-Tone - Ska Hits From The 70's and 80's (1997) F","uid":6957661,"size":415133438,"categoryP":"audio","categoryS":"flac","magnet":"?xt=urn:btih:14418e8daadabee500c5f7427f7178c1563a0ec5&amp;dn=A+Taste+Of+Two-Tone+-+Ska+Hits+From+The+70%5C%27s+and+80%5C%27s+%281997%29+F&amp;tr=udp%3A%2F%2Ftracker.openbittorrent.com%3A80&amp;tr=udp%3A%2F%2Fopen.demonii.com%3A1337&amp;tr=udp%3A%2F%2Ftracker.coppersurfer.tk%3A6969&amp;tr=udp%3A%2F%2Fexodus.desync.com%3A6969","seeders":1,"leechers":0,"uploader":"dfc2tone","files":21,"time":1326644918,"description":"Ripped from original CD using EAC and FLAC Front End.\n\n\nTracklist\n\n    Gangsters The Special A.K.A.\n    Rat Race The Specials\n    On My Radio The Selecter\n    Nelson Mandela The Specials\n    Let's Do Rock Steady The Bodysnatchers\n    Easy Life The Bodysnatchers\n    Jungle Music Rico\n    I Can See Clearly Now Pauline Black\n    Three Minute Hero The Selecter\n    You're Wondering Now The Specials\n    Too Much Too Young The Special A.K.A.\n    Rude Boys Outta Jail Neville Staples\n    A Message To You Rudi The Specials\n    James Bond The Selecter\n    Ruder Than You The Bodysnatchers\n    Mantovani The Swingle Cats\n    Too Much Pressure The Selecter\n    Sea Cruise Rico\n    Carolina Various Artists\n    Ghost Town The Specials\n\n\nPlease seed and enjoy!!","torrent":{"xt":"urn:btih:14418e8daadabee500c5f7427f7178c1563a0ec5","amp;dn":"A+Taste+Of+Two-Tone+-+Ska+Hits+From+The+70%5C%27s+and+80%5C%27s+%281997%29+F","amp;tr":["udp%3A%2F%2Ftracker.openbittorrent.com%3A80","udp%3A%2F%2Fopen.demonii.com%3A1337","udp%3A%2F%2Ftracker.coppersurfer.tk%3A6969","udp%3A%2F%2Fexodus.desync.com%3A6969"],"infoHash":"14418e8daadabee500c5f7427f7178c1563a0ec5","infoHashBuffer":{"type":"Buffer","data":[20,65,142,141,170,218,190,229,0,197,247,66,127,113,120,193,86,58,14,197]},"announce":[],"urlList":[]}}