{"title":"[BreakingAsses] Lady Mai (Oriental Anal / 07.22.2013)","uid":8728666,"size":304293963,"categoryP":"porn","categoryS":"movies","magnet":"?xt=urn:btih:2f41ce33bd41f7fe5d9091faf0ca3d23a9da5eb1&amp;dn=%5BBreakingAsses%5D+Lady+Mai+%28Oriental+Anal+%2F+07.22.2013%29&amp;tr=udp%3A%2F%2Ftracker.openbittorrent.com%3A80&amp;tr=udp%3A%2F%2Fopen.demonii.com%3A1337&amp;tr=udp%3A%2F%2Ftracker.coppersurfer.tk%3A6969&amp;tr=udp%3A%2F%2Fexodus.desync.com%3A6969","seeders":1,"leechers":1,"uploader":"chkm8te","files":2,"time":1374554478,"description":"[BreakingAsses] Lady Mai (Oriental Anal / 07.22.2013)\n\nScreens: &lt;a href=&quot;\nhttp://ima.so/watermark/?img=ce3c437f5cee2fbcec5ec6f62801fea5.jpg&quot; rel=&quot;nofollow&quot; target=&quot;_NEW&quot;&gt;\nhttp://ima.so/watermark/?img=ce3c437f5cee2fbcec5ec6f62801fea5.jpg&lt;/a&gt;","torrent":{"xt":"urn:btih:2f41ce33bd41f7fe5d9091faf0ca3d23a9da5eb1","amp;dn":"%5BBreakingAsses%5D+Lady+Mai+%28Oriental+Anal+%2F+07.22.2013%29","amp;tr":["udp%3A%2F%2Ftracker.openbittorrent.com%3A80","udp%3A%2F%2Fopen.demonii.com%3A1337","udp%3A%2F%2Ftracker.coppersurfer.tk%3A6969","udp%3A%2F%2Fexodus.desync.com%3A6969"],"infoHash":"2f41ce33bd41f7fe5d9091faf0ca3d23a9da5eb1","infoHashBuffer":{"type":"Buffer","data":[47,65,206,51,189,65,247,254,93,144,145,250,240,202,61,35,169,218,94,177]},"announce":[],"urlList":[]}}