{"title":"Big Rich - Block Tested-Hood Approved (2006)","uid":7390554,"size":179045109,"categoryP":"audio","categoryS":"music","magnet":"?xt=urn:btih:3d19ce7ff4142b28c1ed7de32f8fcaf898bdcff8&amp;dn=Big+Rich+-+Block+Tested-Hood+Approved+%282006%29&amp;tr=udp%3A%2F%2Ftracker.openbittorrent.com%3A80&amp;tr=udp%3A%2F%2Fopen.demonii.com%3A1337&amp;tr=udp%3A%2F%2Ftracker.coppersurfer.tk%3A6969&amp;tr=udp%3A%2F%2Fexodus.desync.com%3A6969","seeders":1,"leechers":0,"uploader":"Sackilla666","files":-1,"time":1340759758,"description":"Big Rich - Block Tested-Hood Approved\nKoch Records 2006\n\nTracks:\n\n1.  Big Rich Is Here\n2.  Block Tested Hood Approved\n3.  That's the Business\n4.  Go Crazy \n5.  Where I'm From\n6.  Lay It Down\n7.  It Is What It Is\n8.  Rich Man's World\n9.  To the Top\n10. Got a Problem\n11. How Come?\n12. From Nothing to Something\n13. Elbo Room\n14. Oh\n15. Scrape-n-Scoot\n16. Meet the Dealers\n17. Final Words\n18. F.I.L.L.M.O.E.\n\nIf you like the album then go buy it.  Leave a comment &amp; rate this download please.  If you want bay area music just check out my other uploads.","torrent":{"xt":"urn:btih:3d19ce7ff4142b28c1ed7de32f8fcaf898bdcff8","amp;dn":"Big+Rich+-+Block+Tested-Hood+Approved+%282006%29","amp;tr":["udp%3A%2F%2Ftracker.openbittorrent.com%3A80","udp%3A%2F%2Fopen.demonii.com%3A1337","udp%3A%2F%2Ftracker.coppersurfer.tk%3A6969","udp%3A%2F%2Fexodus.desync.com%3A6969"],"infoHash":"3d19ce7ff4142b28c1ed7de32f8fcaf898bdcff8","infoHashBuffer":{"type":"Buffer","data":[61,25,206,127,244,20,43,40,193,237,125,227,47,143,202,248,152,189,207,248]},"announce":[],"urlList":[]}}