{"title":"Backdoor Entry 2 (2012)","uid":7339616,"size":1463942717,"categoryP":"porn","categoryS":"movies","magnet":"?xt=urn:btih:4461d547d4061fde82219e1d0abd7a40026ef14d&amp;dn=Backdoor+Entry+2+%282012%29&amp;tr=udp%3A%2F%2Ftracker.openbittorrent.com%3A80&amp;tr=udp%3A%2F%2Fopen.demonii.com%3A1337&amp;tr=udp%3A%2F%2Ftracker.coppersurfer.tk%3A6969&amp;tr=udp%3A%2F%2Fexodus.desync.com%3A6969","seeders":1,"leechers":0,"uploader":"Bakelitko","files":5,"time":1339187338,"description":"Screens:\n &lt;a href=&quot;\nhttp://screendir.com/show/8664_backdoor-entry-2-2012-0.jpg&quot; rel=&quot;nofollow&quot; target=&quot;_NEW&quot;&gt;\nhttp://screendir.com/show/8664_backdoor-entry-2-2012-0.jpg&lt;/a&gt;\n &lt;a href=&quot;\nhttp://screendir.com/show/8665_backdoor-entry-2-2012-1.jpg&quot; rel=&quot;nofollow&quot; target=&quot;_NEW&quot;&gt;\nhttp://screendir.com/show/8665_backdoor-entry-2-2012-1.jpg&lt;/a&gt;\n &lt;a href=&quot;\nhttp://screendir.com/show/8666_backdoor-entry-2-2012-2.jpg&quot; rel=&quot;nofollow&quot; target=&quot;_NEW&quot;&gt;\nhttp://screendir.com/show/8666_backdoor-entry-2-2012-2.jpg&lt;/a&gt;\n &lt;a href=&quot;\nhttp://screendir.com/show/8667_backdoor-entry-2-2012-3.jpg&quot; rel=&quot;nofollow&quot; target=&quot;_NEW&quot;&gt;\nhttp://screendir.com/show/8667_backdoor-entry-2-2012-3.jpg&lt;/a&gt;\n &lt;a href=&quot;\nhttp://screendir.com/show/8668_backdoor-entry-2-2012-4.jpg&quot; rel=&quot;nofollow&quot; target=&quot;_NEW&quot;&gt;\nhttp://screendir.com/show/8668_backdoor-entry-2-2012-4.jpg&lt;/a&gt;\n\n","torrent":{"xt":"urn:btih:4461d547d4061fde82219e1d0abd7a40026ef14d","amp;dn":"Backdoor+Entry+2+%282012%29","amp;tr":["udp%3A%2F%2Ftracker.openbittorrent.com%3A80","udp%3A%2F%2Fopen.demonii.com%3A1337","udp%3A%2F%2Ftracker.coppersurfer.tk%3A6969","udp%3A%2F%2Fexodus.desync.com%3A6969"],"infoHash":"4461d547d4061fde82219e1d0abd7a40026ef14d","infoHashBuffer":{"type":"Buffer","data":[68,97,213,71,212,6,31,222,130,33,158,29,10,189,122,64,2,110,241,77]},"announce":[],"urlList":[]}}