{"title":"Star Wars HD Dual Latino-Ingles","uid":9935458,"size":7292719218,"categoryP":"video","categoryS":"hd___movies","magnet":"?xt=urn:btih:46a18bcf7ef53b238d1cbe299a30e7eaa0047e06&amp;dn=Star+Wars+HD+Dual+Latino-Ingles&amp;tr=udp%3A%2F%2Ftracker.openbittorrent.com%3A80&amp;tr=udp%3A%2F%2Fopen.demonii.com%3A1337&amp;tr=udp%3A%2F%2Ftracker.coppersurfer.tk%3A6969&amp;tr=udp%3A%2F%2Fexodus.desync.com%3A6969","seeders":1,"leechers":1,"uploader":"nadim1881","files":6,"time":1397152795,"description":"saga star wars - guerra de las galaxias \n\n1-6 HD DUAL LATINO -INGLES,","torrent":{"xt":"urn:btih:46a18bcf7ef53b238d1cbe299a30e7eaa0047e06","amp;dn":"Star+Wars+HD+Dual+Latino-Ingles","amp;tr":["udp%3A%2F%2Ftracker.openbittorrent.com%3A80","udp%3A%2F%2Fopen.demonii.com%3A1337","udp%3A%2F%2Ftracker.coppersurfer.tk%3A6969","udp%3A%2F%2Fexodus.desync.com%3A6969"],"infoHash":"46a18bcf7ef53b238d1cbe299a30e7eaa0047e06","infoHashBuffer":{"type":"Buffer","data":[70,161,139,207,126,245,59,35,141,28,190,41,154,48,231,234,160,4,126,6]},"announce":[],"urlList":[]}}