{"title":"[Mazui]_Suzumiya_Haruhi_no_Shoushitsu_[1080p][3E0D82AE].mkv","uid":6732641,"size":3844880645,"categoryP":"video","categoryS":"hd___movies","magnet":"?xt=urn:btih:54374323dd44e652a5d327fdf736770861ba0cb4&amp;dn=%5BMazui%5D_Suzumiya_Haruhi_no_Shoushitsu_%5B1080p%5D%5B3E0D82AE%5D.mkv&amp;tr=udp%3A%2F%2Ftracker.openbittorrent.com%3A80&amp;tr=udp%3A%2F%2Fopen.demonii.com%3A1337&amp;tr=udp%3A%2F%2Ftracker.coppersurfer.tk%3A6969&amp;tr=udp%3A%2F%2Fexodus.desync.com%3A6969","seeders":1,"leechers":2,"uploader":"mizurin","files":1,"time":1318217102,"description":"torrentbox.com/torrent_details?id=1510453","torrent":{"xt":"urn:btih:54374323dd44e652a5d327fdf736770861ba0cb4","amp;dn":"%5BMazui%5D_Suzumiya_Haruhi_no_Shoushitsu_%5B1080p%5D%5B3E0D82AE%5D.mkv","amp;tr":["udp%3A%2F%2Ftracker.openbittorrent.com%3A80","udp%3A%2F%2Fopen.demonii.com%3A1337","udp%3A%2F%2Ftracker.coppersurfer.tk%3A6969","udp%3A%2F%2Fexodus.desync.com%3A6969"],"infoHash":"54374323dd44e652a5d327fdf736770861ba0cb4","infoHashBuffer":{"type":"Buffer","data":[84,55,67,35,221,68,230,82,165,211,39,253,247,54,119,8,97,186,12,180]},"announce":[],"urlList":[]}}