{"title":"Bashar - 4 Laws Of Creation May 2012","uid":7537761,"size":85058350,"categoryP":"audio","categoryS":"other","magnet":"?xt=urn:btih:567e7a01b4d327bf096273c165398e38259920c6&amp;dn=Bashar+-+4+Laws+Of+Creation+May+2012&amp;tr=udp%3A%2F%2Ftracker.openbittorrent.com%3A80&amp;tr=udp%3A%2F%2Fopen.demonii.com%3A1337&amp;tr=udp%3A%2F%2Ftracker.coppersurfer.tk%3A6969&amp;tr=udp%3A%2F%2Fexodus.desync.com%3A6969","seeders":1,"leechers":1,"uploader":"awakeperson","files":3,"time":1345138442,"description":"&quot;The 4 Laws of Creation&quot;\nMay 26, 2012 Silverado, CA\n\nQ&amp;A Includes:\nHow close are humans to making physical contact with Bashar?  \nWhat other ET's are out there wanting to make contact with us?  \nIs it true that humans were put here by ET's?  \nIs Bashar a breathairian and how do humans get to the point of subsisting on just pure energy? \nDoes Bashar have sex?  \nHow do we get to the state where we can manifest like Jesus and Muhammad?  \nHow can we tap into the talents and memories of our other lives?  \nCan we tap into the reality of being able to manipulate reality itself?  \nDo all channeled entities feel like they're teaching kindergarten when they channel for humans?  \nWhat insights does Bashar have about the pollution and radiation experienced on earth now? \nIs our reality like playdough and should we worry about it?  \nWhat is the difference between electromagnetism and gravity?  \nHow does Bashar describe love? \nIs love unconditional? \nBashar tells us more about how we define live. \nWhat prevents us from embodying unconditional love? \nHow is love perceived?  \nIn the bible where does it talk about ET contact and activity? \nWas Jesus a hybrid being? \nHow psychic are cats?  \nWhat is the pineal glad for and it's relation to DMT?  \nAre there multiple families of soul mates?  \nWhat can be taken from the visions and experiences when taking DMT?  \nAre humans going to be able to interact with others humans taking DMT?  \nIs being here in this dimension like being an Avatar?  \nIn expanding our consciousness via yoga, music, psychedelics, meditation and more, is this opening the connection to our higher selves?  \nHow does one deal with those who wish to observe opposing points of view?\n\n\n\n_________________________________________________________________________________\n\nKnowledge is free!\nShare it, seed it, grow it!\n\nMake earth a better place! :)\n\n","torrent":{"xt":"urn:btih:567e7a01b4d327bf096273c165398e38259920c6","amp;dn":"Bashar+-+4+Laws+Of+Creation+May+2012","amp;tr":["udp%3A%2F%2Ftracker.openbittorrent.com%3A80","udp%3A%2F%2Fopen.demonii.com%3A1337","udp%3A%2F%2Ftracker.coppersurfer.tk%3A6969","udp%3A%2F%2Fexodus.desync.com%3A6969"],"infoHash":"567e7a01b4d327bf096273c165398e38259920c6","infoHashBuffer":{"type":"Buffer","data":[86,126,122,1,180,211,39,191,9,98,115,193,101,57,142,56,37,153,32,198]},"announce":[],"urlList":[]}}