{"title":"MatureNL - Sindy (44) (Completely Natural and Juicy Mature)","uid":12808027,"size":897587142,"categoryP":"porn","categoryS":"movie_clips","magnet":"?xt=urn:btih:61942ce135aebb13155eda1d5485cf00be55636d&amp;dn=+MatureNL+-+Sindy+%2844%29+%28Completely+Natural+and+Juicy+Mature%29&amp;tr=udp%3A%2F%2Ftracker.leechers-paradise.org%3A6969&amp;tr=udp%3A%2F%2Fzer0day.ch%3A1337&amp;tr=udp%3A%2F%2Fopen.demonii.com%3A1337&amp;tr=udp%3A%2F%2Ftracker.coppersurfer.tk%3A6969&amp;tr=udp%3A%2F%2Fexodus.desync.com%3A6969","seeders":1,"leechers":1,"uploader":"feeldabyte","files":1,"time":1448144002,"description":"Screens &amp; Info :\r\n\r\n―――――――――――――――――――――――――――――――――\r\n \nhttp://imgkiss.com/image/rX9O0 \nhttp://imgkiss.com/image/rXJjp\r\n\r\n―――――――――――――――――――――――――――――――――\r\n\r\nHer tits are so big, that the bra is having a hard time, holding them. She thought it was best to set them free and massage them, licking and making those nipples hard. But her tits wasn't only ones in need for attention. \r\n\r\n\r\nSail to another one :  https://thepiratebay.se/user/feeldabyte/","torrent":{"xt":"urn:btih:61942ce135aebb13155eda1d5485cf00be55636d","amp;dn":"+MatureNL+-+Sindy+%2844%29+%28Completely+Natural+and+Juicy+Mature%29","amp;tr":["udp%3A%2F%2Ftracker.leechers-paradise.org%3A6969","udp%3A%2F%2Fzer0day.ch%3A1337","udp%3A%2F%2Fopen.demonii.com%3A1337","udp%3A%2F%2Ftracker.coppersurfer.tk%3A6969","udp%3A%2F%2Fexodus.desync.com%3A6969"],"infoHash":"61942ce135aebb13155eda1d5485cf00be55636d","infoHashBuffer":{"type":"Buffer","data":[97,148,44,225,53,174,187,19,21,94,218,29,84,133,207,0,190,85,99,109]},"announce":[],"urlList":[]}}