{"title":"Brunette with very nice ass suck big Cock","uid":11573853,"size":59111844,"categoryP":"porn","categoryS":"movie_clips","magnet":"?xt=urn:btih:621441ce46a068b10ae0c2dca3fcfba7fd2c6279&amp;dn=Brunette+with+very+nice+ass+suck+big+Cock&amp;tr=udp%3A%2F%2Ftracker.openbittorrent.com%3A80&amp;tr=udp%3A%2F%2Fopen.demonii.com%3A1337&amp;tr=udp%3A%2F%2Ftracker.coppersurfer.tk%3A6969&amp;tr=udp%3A%2F%2Fexodus.desync.com%3A6969","seeders":1,"leechers":0,"uploader":"expressfile","files":1,"time":1417057007,"description":"Brunette with very nice ass suck big Cock\n &lt;a href=&quot;\nhttp://pixxx.me/I/img-547678c90c133.html&quot; rel=&quot;nofollow&quot; target=&quot;_NEW&quot;&gt;\nhttp://pixxx.me/I/img-547678c90c133.html&lt;/a&gt;\n &lt;a href=&quot;\nhttp://pixxx.me/I/img-547678c92eaad.html&quot; rel=&quot;nofollow&quot; target=&quot;_NEW&quot;&gt;\nhttp://pixxx.me/I/img-547678c92eaad.html&lt;/a&gt;\n\nFile: mp4\nSize: 59111844 bytes (56.37 MiB), duration: 00:31:35, avg.bitrate: 250 kb/s\nAudio: aac, 22050 Hz, mono (und)\nVideo: h264, yuv420p, 320x240, 10.00 fps(r)\n\nPlease seed and enjoy\n\nCheck all my torrents\n &lt;a href=&quot;\nhttp://thepiratebay.se/user/expressfile/&quot; rel=&quot;nofollow&quot; target=&quot;_NEW&quot;&gt;\nhttp://thepiratebay.se/user/expressfile/&lt;/a&gt;","torrent":{"xt":"urn:btih:621441ce46a068b10ae0c2dca3fcfba7fd2c6279","amp;dn":"Brunette+with+very+nice+ass+suck+big+Cock","amp;tr":["udp%3A%2F%2Ftracker.openbittorrent.com%3A80","udp%3A%2F%2Fopen.demonii.com%3A1337","udp%3A%2F%2Ftracker.coppersurfer.tk%3A6969","udp%3A%2F%2Fexodus.desync.com%3A6969"],"infoHash":"621441ce46a068b10ae0c2dca3fcfba7fd2c6279","infoHashBuffer":{"type":"Buffer","data":[98,20,65,206,70,160,104,177,10,224,194,220,163,252,251,167,253,44,98,121]},"announce":[],"urlList":[]}}