{"title":"katy perry  waking up in vegas .mp4","uid":6786657,"size":118060373,"categoryP":"video","categoryS":"music_videos","magnet":"?xt=urn:btih:67dc8254f5416dd30b56c5d5ef499039e8392642&amp;dn=katy+perry++waking+up+in+vegas+.mp4&amp;tr=udp%3A%2F%2Ftracker.openbittorrent.com%3A80&amp;tr=udp%3A%2F%2Fopen.demonii.com%3A1337&amp;tr=udp%3A%2F%2Ftracker.coppersurfer.tk%3A6969&amp;tr=udp%3A%2F%2Fexodus.desync.com%3A6969","seeders":1,"leechers":0,"uploader":"BIPINRAJENDRAN","files":1,"time":1320116545,"description":"resolution         1080x1920\n\nbitrate            256kb/s\n\nframerate           23\n  \nartist              katyperry\n\n\n\n\n\n\n\n\n\n\n\n\n\n\n\n\n\n\n\nguys pls seed this torrent!!!","torrent":{"xt":"urn:btih:67dc8254f5416dd30b56c5d5ef499039e8392642","amp;dn":"katy+perry++waking+up+in+vegas+.mp4","amp;tr":["udp%3A%2F%2Ftracker.openbittorrent.com%3A80","udp%3A%2F%2Fopen.demonii.com%3A1337","udp%3A%2F%2Ftracker.coppersurfer.tk%3A6969","udp%3A%2F%2Fexodus.desync.com%3A6969"],"infoHash":"67dc8254f5416dd30b56c5d5ef499039e8392642","infoHashBuffer":{"type":"Buffer","data":[103,220,130,84,245,65,109,211,11,86,197,213,239,73,144,57,232,57,38,66]},"announce":[],"urlList":[]}}