{"title":"Andre Rieu - Life Is Beutiful - 2000 Gala Millennium Concert (Su","uid":3468639,"size":6153,"categoryP":"video","categoryS":"music_videos","magnet":"?xt=urn:btih:67de2f75e206daacae4063d371a9ce9236ace859&amp;dn=Andre+Rieu+-+Life+Is+Beutiful+-+2000+Gala+Millennium+Concert+%28Su&amp;tr=udp%3A%2F%2Ftracker.openbittorrent.com%3A80&amp;tr=udp%3A%2F%2Fopen.demonii.com%3A1337&amp;tr=udp%3A%2F%2Ftracker.coppersurfer.tk%3A6969&amp;tr=udp%3A%2F%2Fexodus.desync.com%3A6969","seeders":1,"leechers":0,"uploader":"!ntruder","files":1,"time":1144598137,"description":"Subtitles in portugese(Brazil) and english.","torrent":{"xt":"urn:btih:67de2f75e206daacae4063d371a9ce9236ace859","amp;dn":"Andre+Rieu+-+Life+Is+Beutiful+-+2000+Gala+Millennium+Concert+%28Su","amp;tr":["udp%3A%2F%2Ftracker.openbittorrent.com%3A80","udp%3A%2F%2Fopen.demonii.com%3A1337","udp%3A%2F%2Ftracker.coppersurfer.tk%3A6969","udp%3A%2F%2Fexodus.desync.com%3A6969"],"infoHash":"67de2f75e206daacae4063d371a9ce9236ace859","infoHashBuffer":{"type":"Buffer","data":[103,222,47,117,226,6,218,172,174,64,99,211,113,169,206,146,54,172,232,89]},"announce":[],"urlList":[]}}