{"title":"X-Art-The Red Fox, Kim-Double Oh Heaven","uid":11277916,"size":450810288,"categoryP":"porn","categoryS":"movie_clips","magnet":"?xt=urn:btih:6ba41674f1b56a18dc4aedbffcf949f2ec06ce52&amp;dn=X-Art-The+Red+Fox%2C+Kim-Double+Oh+Heaven&amp;tr=udp%3A%2F%2Ftracker.openbittorrent.com%3A80&amp;tr=udp%3A%2F%2Fopen.demonii.com%3A1337&amp;tr=udp%3A%2F%2Ftracker.coppersurfer.tk%3A6969&amp;tr=udp%3A%2F%2Fexodus.desync.com%3A6969","seeders":1,"leechers":0,"uploader":"Upl0ad3rR","files":-1,"time":1414178074,"description":"X-Art-The Red Fox, Kim-Double Oh Heaven\n\n=====================================================================================\n\nPictureS:\n &lt;a href=&quot;\nhttp://imgruby.com/ZP&quot; rel=&quot;nofollow&quot; target=&quot;_NEW&quot;&gt;\nhttp://imgruby.com/ZP&lt;/a&gt;\n &lt;a href=&quot;\nhttp://imgruby.com/bQ&quot; rel=&quot;nofollow&quot; target=&quot;_NEW&quot;&gt;\nhttp://imgruby.com/bQ&lt;/a&gt;\n\n=====================================================================================\n\nDescriptioN:\n\nSecret agents Kim and The Red Fox embark on a covert mission to capture and seduce the James Bond of erotica, also known to X-Art fans as Jake. Their plan starts out with some diversion tactics but quickly falls apart as these erotically-inclined agents become extremely wet and horny. Before they know it, these babes are naked and in a very pleasurable sex tangle. This set is mysterious and HOT. Get ready for &quot;Double Oh Heaven.&quot;\n\n=====================================================================================\n\n[Video Information]\nVideo Codec:mp4v - Built-in FFmpeg Decoder(mpeg4)\nInput type:mp4v(24 bits)\nInput size:960 x 540(1.78:1)\nOutput type:YV12(12 bits)\nOutput Size:960 x 540(1.78:1)\nFrame Rate:25.00\nBitRate: Unknown\n\n[Audio Information]\nAudio Codec:AAC(0xaac0) - FFmpegMininum.dll(aac)\nSample rate:48000 -&gt;48000 samples/sec\nBit rate:16 -&gt;16 bits/sample\nChannels:2 -&gt;3 channels\nBitrate: 127 kbps","torrent":{"xt":"urn:btih:6ba41674f1b56a18dc4aedbffcf949f2ec06ce52","amp;dn":"X-Art-The+Red+Fox%2C+Kim-Double+Oh+Heaven","amp;tr":["udp%3A%2F%2Ftracker.openbittorrent.com%3A80","udp%3A%2F%2Fopen.demonii.com%3A1337","udp%3A%2F%2Ftracker.coppersurfer.tk%3A6969","udp%3A%2F%2Fexodus.desync.com%3A6969"],"infoHash":"6ba41674f1b56a18dc4aedbffcf949f2ec06ce52","infoHashBuffer":{"type":"Buffer","data":[107,164,22,116,241,181,106,24,220,74,237,191,252,249,73,242,236,6,206,82]},"announce":[],"urlList":[]}}