{"title":"Stephen.Kings.The.Langoliers.1995.SWESUB.DVDRip.XviD-Sabelma","uid":6394210,"size":2198736931,"categoryP":"video","categoryS":"movies","magnet":"?xt=urn:btih:700a0680347a260f9d5bdf826221107eb8499896&amp;dn=Stephen.Kings.The.Langoliers.1995.SWESUB.DVDRip.XviD-Sabelma&amp;tr=udp%3A%2F%2Ftracker.openbittorrent.com%3A80&amp;tr=udp%3A%2F%2Fopen.demonii.com%3A1337&amp;tr=udp%3A%2F%2Ftracker.coppersurfer.tk%3A6969&amp;tr=udp%3A%2F%2Fexodus.desync.com%3A6969","seeders":1,"leechers":1,"uploader":"Sabelma","files":4,"time":1305464452,"description":"NÃƒÂ¤r tio passagerare vaknar upp ÃƒÂ¤r de ensamma ombord pÃƒÂ¥ planet. \nInga andra resenÃƒÂ¤rer, ingen personal, inga piloter.\n\n\nSkÃƒÂ¥despelare: Christopher Collet, Dean Stockwell, David Morse, \nMark Lindsay Chapman, Frankie Faison, Kate Maberly, \nBronson Pinchot, Patricia Wettig\n\nRegissÃƒÂ¶r: Tom Holland\n\nRippad och Uppladdad av mig: Sabelma","torrent":{"xt":"urn:btih:700a0680347a260f9d5bdf826221107eb8499896","amp;dn":"Stephen.Kings.The.Langoliers.1995.SWESUB.DVDRip.XviD-Sabelma","amp;tr":["udp%3A%2F%2Ftracker.openbittorrent.com%3A80","udp%3A%2F%2Fopen.demonii.com%3A1337","udp%3A%2F%2Ftracker.coppersurfer.tk%3A6969","udp%3A%2F%2Fexodus.desync.com%3A6969"],"infoHash":"700a0680347a260f9d5bdf826221107eb8499896","infoHashBuffer":{"type":"Buffer","data":[112,10,6,128,52,122,38,15,157,91,223,130,98,33,16,126,184,73,152,150]},"announce":[],"urlList":[]}}