{"title":"Arthur Newman (2012) LIMITED BluRay 720p 650MB Ganool","uid":8838242,"size":682120138,"categoryP":"video","categoryS":"hd___movies","magnet":"?xt=urn:btih:7a5213d9c0b57e95b1faf2cb42f40f909e124f41&amp;dn=Arthur+Newman+%282012%29+LIMITED+BluRay+720p+650MB+Ganool&amp;tr=udp%3A%2F%2Ftracker.openbittorrent.com%3A80&amp;tr=udp%3A%2F%2Fopen.demonii.com%3A1337&amp;tr=udp%3A%2F%2Ftracker.coppersurfer.tk%3A6969&amp;tr=udp%3A%2F%2Fexodus.desync.com%3A6969","seeders":1,"leechers":0,"uploader":".BONE.","files":-1,"time":1377181385,"description":"A story of a man who fakes his own death and assumes a new identity in order to escape his life, who then moves in with a woman who is also trying to leave her past behind.\n\nInfo: http://www.imdb.com/title/tt1930546/\nRelease Date: 13 June 2013 (Kuwait)\nGenre: Comedy | Drama\nStars : Colin Firth, Emily Blunt, Anne Heche\nQuality: BluRay 720p\nEncoder: SHQ@Ganool\nSource: 720p BluRay x264-GECKOS\nSize: 650MB","torrent":{"xt":"urn:btih:7a5213d9c0b57e95b1faf2cb42f40f909e124f41","amp;dn":"Arthur+Newman+%282012%29+LIMITED+BluRay+720p+650MB+Ganool","amp;tr":["udp%3A%2F%2Ftracker.openbittorrent.com%3A80","udp%3A%2F%2Fopen.demonii.com%3A1337","udp%3A%2F%2Ftracker.coppersurfer.tk%3A6969","udp%3A%2F%2Fexodus.desync.com%3A6969"],"infoHash":"7a5213d9c0b57e95b1faf2cb42f40f909e124f41","infoHashBuffer":{"type":"Buffer","data":[122,82,19,217,192,181,126,149,177,250,242,203,66,244,15,144,158,18,79,65]},"announce":[],"urlList":[]}}