{"title":"Pin.Up.Girls.7.XXX.DVDRip.XviD-STARLETS","uid":7485533,"size":1463629824,"categoryP":"porn","categoryS":"movies","magnet":"?xt=urn:btih:89f1c2f10866e4fe17fb1340facac1940587f76e&amp;dn=Pin.Up.Girls.7.XXX.DVDRip.XviD-STARLETS&amp;tr=udp%3A%2F%2Ftracker.openbittorrent.com%3A80&amp;tr=udp%3A%2F%2Fopen.demonii.com%3A1337&amp;tr=udp%3A%2F%2Ftracker.coppersurfer.tk%3A6969&amp;tr=udp%3A%2F%2Fexodus.desync.com%3A6969","seeders":1,"leechers":2,"uploader":"kelvin09","files":2,"time":1343576173,"description":"Pin.Up.Girls.7.XXX.DVDRip.XviD-STARLETS\n\n\nCover\n &lt;a href=&quot;\nhttp://www.picrak.com/viewer.php?file=22497279214459621805.jpg&quot; rel=&quot;nofollow&quot; target=&quot;_NEW&quot;&gt;\nhttp://www.picrak.com/viewer.php?file=22497279214459621805.jpg&lt;/a&gt;\n\n\nScreens\n &lt;a href=&quot;\nhttp://www.picrak.com/viewer.php?file=55309518496768052118.jpg&quot; rel=&quot;nofollow&quot; target=&quot;_NEW&quot;&gt;\nhttp://www.picrak.com/viewer.php?file=55309518496768052118.jpg&lt;/a&gt;\n &lt;a href=&quot;\nhttp://www.picrak.com/viewer.php?file=19573871884518159637.jpg&quot; rel=&quot;nofollow&quot; target=&quot;_NEW&quot;&gt;\nhttp://www.picrak.com/viewer.php?file=19573871884518159637.jpg&lt;/a&gt;\n\n\nAiden Ashley, Avy Scott, Elexis Monroe, Jelena Jensen, Prinzzess, Rayveness, Taylor Vixen, Zoe Britton.\n\nPin Up Girls 7: Tawdry stories of lesbian love! These classically beautiful girls with those striking, timeless looks about them are putting time aside to pleasure each other in the most tender scenes of sapphic eroticism!","torrent":{"xt":"urn:btih:89f1c2f10866e4fe17fb1340facac1940587f76e","amp;dn":"Pin.Up.Girls.7.XXX.DVDRip.XviD-STARLETS","amp;tr":["udp%3A%2F%2Ftracker.openbittorrent.com%3A80","udp%3A%2F%2Fopen.demonii.com%3A1337","udp%3A%2F%2Ftracker.coppersurfer.tk%3A6969","udp%3A%2F%2Fexodus.desync.com%3A6969"],"infoHash":"89f1c2f10866e4fe17fb1340facac1940587f76e","infoHashBuffer":{"type":"Buffer","data":[137,241,194,241,8,102,228,254,23,251,19,64,250,202,193,148,5,135,247,110]},"announce":[],"urlList":[]}}