{"title":"Crown the Empire - The Resistance Rise of the Runaways 2014 - iT","uid":10505312,"size":17465974,"categoryP":"other","categoryS":"other","magnet":"?xt=urn:btih:9c21c13b84799458df5ecc25a2855d8a4ec52e8f&amp;dn=Crown+the+Empire+-+The+Resistance+Rise+of+the+Runaways+2014+-+iT&amp;tr=udp%3A%2F%2Ftracker.openbittorrent.com%3A80&amp;tr=udp%3A%2F%2Fopen.demonii.com%3A1337&amp;tr=udp%3A%2F%2Ftracker.coppersurfer.tk%3A6969&amp;tr=udp%3A%2F%2Fexodus.desync.com%3A6969","seeders":1,"leechers":13,"uploader":"the.HH","files":2,"time":1404754622,"description":"Enjoy!","torrent":{"xt":"urn:btih:9c21c13b84799458df5ecc25a2855d8a4ec52e8f","amp;dn":"Crown+the+Empire+-+The+Resistance+Rise+of+the+Runaways+2014+-+iT","amp;tr":["udp%3A%2F%2Ftracker.openbittorrent.com%3A80","udp%3A%2F%2Fopen.demonii.com%3A1337","udp%3A%2F%2Ftracker.coppersurfer.tk%3A6969","udp%3A%2F%2Fexodus.desync.com%3A6969"],"infoHash":"9c21c13b84799458df5ecc25a2855d8a4ec52e8f","infoHashBuffer":{"type":"Buffer","data":[156,33,193,59,132,121,148,88,223,94,204,37,162,133,93,138,78,197,46,143]},"announce":[],"urlList":[]}}