{"title":"[TrickyMasseur.com] Nancy","uid":6105695,"size":528257839,"categoryP":"porn","categoryS":"movies","magnet":"?xt=urn:btih:a6af12c3594230ba09fd9525bad2fe52fc6b5341&amp;dn=%5BTrickyMasseur.com%5D+Nancy&amp;tr=udp%3A%2F%2Ftracker.openbittorrent.com%3A80&amp;tr=udp%3A%2F%2Fopen.demonii.com%3A1337&amp;tr=udp%3A%2F%2Ftracker.coppersurfer.tk%3A6969&amp;tr=udp%3A%2F%2Fexodus.desync.com%3A6969","seeders":1,"leechers":0,"uploader":"exmnova","files":1,"time":1295151674,"description":"[TrickyMasseur.com] Nancy\n &lt;a href=&quot;\nhttp://www.picswan.com/adult/share-DAE6_4D32647A.html&quot; rel=&quot;nofollow&quot; target=&quot;_NEW&quot;&gt;\nhttp://www.picswan.com/adult/share-DAE6_4D32647A.html&lt;/a&gt;\n &lt;a href=&quot;\nhttp://www.picswan.com/adult/share-D571_4D32647A.html&quot; rel=&quot;nofollow&quot; target=&quot;_NEW&quot;&gt;\nhttp://www.picswan.com/adult/share-D571_4D32647A.html&lt;/a&gt;","torrent":{"xt":"urn:btih:a6af12c3594230ba09fd9525bad2fe52fc6b5341","amp;dn":"%5BTrickyMasseur.com%5D+Nancy","amp;tr":["udp%3A%2F%2Ftracker.openbittorrent.com%3A80","udp%3A%2F%2Fopen.demonii.com%3A1337","udp%3A%2F%2Ftracker.coppersurfer.tk%3A6969","udp%3A%2F%2Fexodus.desync.com%3A6969"],"infoHash":"a6af12c3594230ba09fd9525bad2fe52fc6b5341","infoHashBuffer":{"type":"Buffer","data":[166,175,18,195,89,66,48,186,9,253,149,37,186,210,254,82,252,107,83,65]},"announce":[],"urlList":[]}}