{"title":"WWE RAW 2016 05 02 HDTV x264-Ebi [TJET]","uid":14510175,"size":1466677565,"categoryP":"video","categoryS":"tv_shows","magnet":"?xt=urn:btih:b200da1bc412c15a0b66f3a0d1a2b9f1590ec030&amp;dn=+WWE+RAW+2016+05+02+HDTV+x264-Ebi+%5BTJET%5D&amp;tr=udp%3A%2F%2Ftracker.leechers-paradise.org%3A6969&amp;tr=udp%3A%2F%2Fzer0day.ch%3A1337&amp;tr=udp%3A%2F%2Fopen.demonii.com%3A1337&amp;tr=udp%3A%2F%2Ftracker.coppersurfer.tk%3A6969&amp;tr=udp%3A%2F%2Fexodus.desync.com%3A6969","seeders":1,"leechers":0,"uploader":"CenaCme","files":2,"time":1462259410,"description":"WWE.RAW.2016.05.02.HDTV.x264-Ebi\r\nRelease Info:\r\nShow Name: WWE Monday Night RAW\r\nGenre: Wrestling\r\nRelease Date: 2016-05-03(UK)\r\nAir Date: 2016-05-02(US)\r\nSource : HDTV\r\nContainer: MP4\r\nVideo: x264, 1466Kbps, 29,970fps, 712x400, 16:9\r\nAudio: AAC, 160Kbps, 48KHz, 2ch\r\nSize: 1.37 GB\r\nRuntime: 2h 13mn 22s\r\n\r\n\r\nThumb sheet:\r\n \nhttps://extraimago.com/image/alX1","torrent":{"xt":"urn:btih:b200da1bc412c15a0b66f3a0d1a2b9f1590ec030","amp;dn":"+WWE+RAW+2016+05+02+HDTV+x264-Ebi+%5BTJET%5D","amp;tr":["udp%3A%2F%2Ftracker.leechers-paradise.org%3A6969","udp%3A%2F%2Fzer0day.ch%3A1337","udp%3A%2F%2Fopen.demonii.com%3A1337","udp%3A%2F%2Ftracker.coppersurfer.tk%3A6969","udp%3A%2F%2Fexodus.desync.com%3A6969"],"infoHash":"b200da1bc412c15a0b66f3a0d1a2b9f1590ec030","infoHashBuffer":{"type":"Buffer","data":[178,0,218,27,196,18,193,90,11,102,243,160,209,162,185,241,89,14,192,48]},"announce":[],"urlList":[]}}