{"title":"Kangaroo Court konsert Trondheim mai 07","uid":3910495,"size":974508124,"categoryP":"video","categoryS":"movies","magnet":"?xt=urn:btih:b7eff766a9dd5b41c9c847ff96df29104349fe3c&amp;dn=Kangaroo+Court+konsert+Trondheim+mai+07&amp;tr=udp%3A%2F%2Ftracker.openbittorrent.com%3A80&amp;tr=udp%3A%2F%2Fopen.demonii.com%3A1337&amp;tr=udp%3A%2F%2Ftracker.coppersurfer.tk%3A6969&amp;tr=udp%3A%2F%2Fexodus.desync.com%3A6969","seeders":1,"leechers":0,"uploader":"Kynxx","files":1,"time":1196115030,"description":"Kangaroo Court konsert. Spilt inn pÃƒ?Ã‚Â¥ ISAK","torrent":{"xt":"urn:btih:b7eff766a9dd5b41c9c847ff96df29104349fe3c","amp;dn":"Kangaroo+Court+konsert+Trondheim+mai+07","amp;tr":["udp%3A%2F%2Ftracker.openbittorrent.com%3A80","udp%3A%2F%2Fopen.demonii.com%3A1337","udp%3A%2F%2Ftracker.coppersurfer.tk%3A6969","udp%3A%2F%2Fexodus.desync.com%3A6969"],"infoHash":"b7eff766a9dd5b41c9c847ff96df29104349fe3c","infoHashBuffer":{"type":"Buffer","data":[183,239,247,102,169,221,91,65,201,200,71,255,150,223,41,16,67,73,254,60]},"announce":[],"urlList":[]}}