{"title":"Digital SLR Photography - March 2014  UK","uid":9553505,"size":53164518,"categoryP":"other","categoryS":"e_books","magnet":"?xt=urn:btih:bd837280ac575eabfe0172e9c52c23ab7242c18e&amp;dn=Digital+SLR+Photography+-+March+2014++UK&amp;tr=udp%3A%2F%2Ftracker.openbittorrent.com%3A80&amp;tr=udp%3A%2F%2Fopen.demonii.com%3A1337&amp;tr=udp%3A%2F%2Ftracker.coppersurfer.tk%3A6969&amp;tr=udp%3A%2F%2Fexodus.desync.com%3A6969","seeders":1,"leechers":0,"uploader":"bpfine","files":-1,"time":1391311504,"description":"\nDigital SLR Photography - March 2014  UK\n\n148 Pages | True PDF | English | 50 MB \n\n\nDigital SLR Photography addresses the needs of today's photographer in a lively, informative and stylish format. Dedicated to digital SLR photographers of all abilities, from beginner through enthusiast to professional it will inform and entertain you through a unique blend of technique articles, inspirational images, news and authoritative reviews. Covering topics such as landscapes, portraits and close up photography, this magazine provides a focused and comprehensive read guaranteed to help you get the most out of your photography.\n\n\n","torrent":{"xt":"urn:btih:bd837280ac575eabfe0172e9c52c23ab7242c18e","amp;dn":"Digital+SLR+Photography+-+March+2014++UK","amp;tr":["udp%3A%2F%2Ftracker.openbittorrent.com%3A80","udp%3A%2F%2Fopen.demonii.com%3A1337","udp%3A%2F%2Ftracker.coppersurfer.tk%3A6969","udp%3A%2F%2Fexodus.desync.com%3A6969"],"infoHash":"bd837280ac575eabfe0172e9c52c23ab7242c18e","infoHashBuffer":{"type":"Buffer","data":[189,131,114,128,172,87,94,171,254,1,114,233,197,44,35,171,114,66,193,142]},"announce":[],"urlList":[]}}