{"title":"Katy Perry - E.T ( Remix ).mp3","uid":6582875,"size":8372675,"categoryP":"audio","categoryS":"music","magnet":"?xt=urn:btih:bec3c18a2c06e778afddf5aeaa0ab4e225e72758&amp;dn=Katy+Perry+-+E.T+%28+Remix+%29.mp3&amp;tr=udp%3A%2F%2Ftracker.openbittorrent.com%3A80&amp;tr=udp%3A%2F%2Fopen.demonii.com%3A1337&amp;tr=udp%3A%2F%2Ftracker.coppersurfer.tk%3A6969&amp;tr=udp%3A%2F%2Fexodus.desync.com%3A6969","seeders":1,"leechers":0,"uploader":"EchoscapeRecords","files":-1,"time":1312486964,"description":"KATY PERRY - E.T REMIX","torrent":{"xt":"urn:btih:bec3c18a2c06e778afddf5aeaa0ab4e225e72758","amp;dn":"Katy+Perry+-+E.T+%28+Remix+%29.mp3","amp;tr":["udp%3A%2F%2Ftracker.openbittorrent.com%3A80","udp%3A%2F%2Fopen.demonii.com%3A1337","udp%3A%2F%2Ftracker.coppersurfer.tk%3A6969","udp%3A%2F%2Fexodus.desync.com%3A6969"],"infoHash":"bec3c18a2c06e778afddf5aeaa0ab4e225e72758","infoHashBuffer":{"type":"Buffer","data":[190,195,193,138,44,6,231,120,175,221,245,174,170,10,180,226,37,231,39,88]},"announce":[],"urlList":[]}}