{"title":"PervsOnPatrol - Uma Jolie (Rescued Spinner Sucks Dick) NEW 19 No","uid":12791388,"size":343988807,"categoryP":"porn","categoryS":"movie_clips","magnet":"?xt=urn:btih:c579aae9df1cd723737a3efd49702211bbc213d5&amp;dn=PervsOnPatrol+-+Uma+Jolie+%28Rescued+Spinner+Sucks+Dick%29+NEW+19+No&amp;tr=udp%3A%2F%2Ftracker.leechers-paradise.org%3A6969&amp;tr=udp%3A%2F%2Fzer0day.ch%3A1337&amp;tr=udp%3A%2F%2Fopen.demonii.com%3A1337&amp;tr=udp%3A%2F%2Ftracker.coppersurfer.tk%3A6969&amp;tr=udp%3A%2F%2Fexodus.desync.com%3A6969","seeders":1,"leechers":1,"uploader":"xxxlavalxxx","files":2,"time":1447923161,"description":"Alone on the beach, Uma Jolie finds herself in need of rescuing when some rude asshole asks to see her tits. Lucky for Uma, she meets a gentleman who sweeps her off her feet, takes her up to his penthouse, and fucks her fine little pussy senseless.\r\nTags: Outdoors, Sex, Deep Throat, Doggystyle, Cowgirl, Reverse Cowgirl, Missionary\r\n \nhttp://imgdone.com/viewer.php?file=13647886683880911563.jpg\r\n \nhttp://imgdone.com/viewer.php?file=04567437102795056545.jpg","torrent":{"xt":"urn:btih:c579aae9df1cd723737a3efd49702211bbc213d5","amp;dn":"PervsOnPatrol+-+Uma+Jolie+%28Rescued+Spinner+Sucks+Dick%29+NEW+19+No","amp;tr":["udp%3A%2F%2Ftracker.leechers-paradise.org%3A6969","udp%3A%2F%2Fzer0day.ch%3A1337","udp%3A%2F%2Fopen.demonii.com%3A1337","udp%3A%2F%2Ftracker.coppersurfer.tk%3A6969","udp%3A%2F%2Fexodus.desync.com%3A6969"],"infoHash":"c579aae9df1cd723737a3efd49702211bbc213d5","infoHashBuffer":{"type":"Buffer","data":[197,121,170,233,223,28,215,35,115,122,62,253,73,112,34,17,187,194,19,213]},"announce":[],"urlList":[]}}