{"title":"Chartbuster Essential Plus Karaoke CBEP497 - KaraokeRG","uid":10058338,"size":927268565,"categoryP":"audio","categoryS":"other","magnet":"?xt=urn:btih:d1007387b288047db9bf72aac78aab67dc6038c0&amp;dn=Chartbuster+Essential+Plus+Karaoke+CBEP497+-+KaraokeRG&amp;tr=udp%3A%2F%2Ftracker.openbittorrent.com%3A80&amp;tr=udp%3A%2F%2Fopen.demonii.com%3A1337&amp;tr=udp%3A%2F%2Ftracker.coppersurfer.tk%3A6969&amp;tr=udp%3A%2F%2Fexodus.desync.com%3A6969","seeders":1,"leechers":0,"uploader":"KaraokeRG","files":-1,"time":1398695746,"description":"KaraokeRG is a new Release Group dedicated to new,clean karaoke uploads.            \nAll our uploaders have been Trusted &amp; Verified for some years.\nBeware of Fake uploaders,check our username first.\nDo not ask to be an uploader,YOU will be asked.\nPlease comment if you enjoy our uploads &amp; please seed back.\n\n\nChartbuster Essential Plus Karaoke CBEP497 \n\n\nRelease Date:Unknown\nPublisher:Chartbuster Karaoke\nUploaded By:KaraokeRG\nFile Size:884MB\nFormat:MP3/CD+G\nBit Rate:256kbps\nContains:200Files\nPassword Protection:None\n\n\nTrack List\n\n\n01. Cbep497-1-01 - Pipkins, The - Gimme Dat Ding\n02. Cbep497-1-02 - Mungo Jerry - In The Summertime\n03. Cbep497-1-03 - Taylor, R. Dean - Indiana Wants Me\n04. Cbep497-1-04 - George Baker Selection, The - Little Green Bag\n05. Cbep497-1-05 - Tee Set, The - Ma Belle Amie\n06. Cbep497-1-06 - Bloom, Bobby - Montego Bay\n07. Cbep497-1-07 - White Plains - My Baby Loves Lovin'\n08. Cbep497-1-08 - Marmalade - Reflections Of My Life\n09. Cbep497-1-09 - Burdon, Eric &amp; War - Spill The Wine\n10. Cbep497-1-10 - Alive &amp; Kicking - Tighter, Tighter\n11. Cbep497-1-11 - Band, The - Up On Cripple Creek\n12. Cbep497-1-12 - Ides Of March, The - Vehicle\n13. Cbep497-1-13 - Poppy Family &amp; Susan Jacks - Which Way Are You Goin', Billy\n14. Cbep497-1-14 - Christie - Yellow River\n15. Cbep497-1-15 - Michaels, Lee - Do You Know What I Mean\n16. Cbep497-1-16 - Edmunds, Dave - I Hear You Knockin'\n17. Cbep497-1-17 - Free Movement, The - I've Found Someone Of My Own\n\n01. Cbep497-2-01 - Basil, Toni - Mickey\n02. Cbep497-2-02 - Undisputed Truth - Smiling Faces Sometimes\n03. Cbep497-2-03 - Stampeders, The - Sweet City Woman\n04. Cbep497-2-04 - Rex, T. - Bang A Gong\n05. Cbep497-2-05 - Boone, Daniel - Beautiful Sunday\n06. Cbep497-2-06 - Uriah Heep - Easy Livin'\n07. Cbep497-2-07 - O'keefe, Danny - Good Time Charlie's Got The Blues\n08. Cbep497-2-08 - Argent - Hold Your Head Up\n09. Cbep497-2-09 - Commander Cody &amp; His Lost Planet Airmen - Hot Rod Lincoln\n10. Cbep497-2-10 - Hammond, Albert - It Never Rains In Southern California\n11. Cbep497-2-11 - Jonathon Edwards - Sunshine\n12. Cbep497-2-12 - New York City - I'm Doin' Fine Now\n13. Cbep497-2-13 - Hurricane Smith - Oh, Babe, What Would You Say\n14. Cbep497-2-14 - Holmes, Clint - Playground In My Mind\n15. Cbep497-2-15 - Stealers Wheel - Stuck In The Middle With You\n16. Cbep497-2-16 - Thomas, Timmy - Why Can't We Live Together\n17. Cbep497-2-17 - Devaughn, William - Be Thankful For What You Got\n\n01. Cbep497-3-01 - Redbone - Come &amp; Get Your Love\n02. Cbep497-3-02 - Defranco Family &amp; Tony Defranco - Heartbeat-It's A Lovebeat\n03. Cbep497-3-03 - Douglas, Carl - Kung Fu Fighting\n04. Cbep497-3-04 - Reunion - Life Is A Rock (But The Radio Rolled Me)\n05. Cbep497-3-05 - Ian, Janis - At Seventeen\n06. Cbep497-3-06 - Wakelin, Johnny &amp; The Kinshasa Band - Black Superman-'Muhammad Ali'\n07. Cbep497-3-07 - Pilot - Magic\n08. Cbep497-3-08 - Snow, Phoebe - Poetry Man\n09. Cbep497-3-09 - Thin Lizzy - Boys Are Back In Town, The\n10. Cbep497-3-10 - Tavares - Heaven Must Be Missing An Angel\n11. Cbep497-3-11 - Starbuck - Moonlight Feels Right\n12. Cbep497-3-12 - Sebastian, John - Welcome Back\n13. Cbep497-3-13 - Floaters, The - Float On\n14. Cbep497-3-14 - Nicholas, Paul - Heaven On The 7Th Floor\n15. Cbep497-3-15 - Dundas, David - Jeans On\n16. Cbep497-3-16 - Gold, Andrew - Lonely Boy\n\n01. Cbep497-4-01 - Bishop, Stephen - On And On\n02. Cbep497-4-02 - Welch, Bob - Sentimental Lady\n03. Cbep497-4-03 - Stewart, Al - Year Of The Cat\n04. Cbep497-4-04 - Rafferty, Gerry - Baker Street\n05. Cbep497-4-05 - Rea, Chris - Fool (If You Think It's Over)\n06. Cbep497-4-06 - Michael Zager Band, The - Let's All Chant\n07. Cbep497-4-07 - Young, John Paul - Love Is In The Air\n08. Cbep497-4-08 - Jones, Rickie Lee - Chuck E.'S In Love\n09. Cbep497-4-09 - Mills, Stephanie - Never Knew Love Like This Before\n10. Cbep497-4-10 - Quatro, Suzi &amp; Chris Norman - Stumblin' In\n11. Cbep497-4-11 - Caldwell, Bobby - What You Won't Do For Love\n12. Cbep497-4-12 - Souther, J.D. - You're Only Lonely\n13. Cbep497-4-13 - Numan, Gary - Cars\n14. Cbep497-4-14 - Korgis, The - Everybody's Got To Learn Sometime\n15. Cbep497-4-15 - Townshend, Pete - Let My Love Open The Door\n16. Cbep497-4-16 - Shalamar - Second Time Around, The\n17. Cbep497-4-17 - S.O.S. Band, The - Take Your Time (Do It Right)\n\n01. Cbep497-5-01 - Rocky Burnette - Tired Of Toein' The Line\n02. Cbep497-5-02 - Vapors - Turning Japanese\n03. Cbep497-5-03 - Quarterflash - Harden My Heart\n04. Cbep497-5-04 - Soft Cell - Tainted Love\n05. Cbep497-5-05 - Talking Heads - Burning Down The House\n06. Cbep497-5-06 - Greg Kihn Band, The - Jeopardy\n07. Cbep497-5-07 - Musical Youth - Pass The Dutchie\n08. Cbep497-5-08 - Romantics, The - Talking In Your Sleep\n09. Cbep497-5-09 - Spandau Ballet - True\n10. Cbep497-5-10 - Nena - 99 Red Balloons\n11. Cbep497-5-11 - Wagner, Jack - All I Need\n12. Cbep497-5-12 - Ollie &amp; Jerry - Breakin' There's No Stopping Us\n13. Cbep497-5-13 - Jump 'N The Saddle - Curly Shuffle, The\n14. Cbep497-5-14 - Bailey, Phillip - Easy Lover\n15. Cbep497-5-15 - Honeydrippers, The - Sea Of Love\n16. Cbep497-5-16 - Ullman, Tracy - They Don't Know\n17. Cbep497-5-17 - Arcadia - Election Day\n\n01. Cbep497-6-01 - Power Station - Some Like It Hot\n02. Cbep497-6-02 - Til Tuesday - Voices Carry\n03. Cbep497-6-03 - Timex Social Club - Rumors\n04. Cbep497-6-04 - Stacey Q. - Two Of Hearts\n05. Cbep497-6-05 - Stewart, Jermaine - We Don't Have To Take Our Clothes Off\n06. Cbep497-6-06 - Swing Out Sister - Breakout\n07. Cbep497-6-07 - System - Don't Disturb This Groove\n08. Cbep497-6-08 - T'pau - Heart &amp; Soul\n09. Cbep497-6-09 - Whispers, The - Rock Steady\n10. Cbep497-6-10 - When In Rome - Promise, The\n11. Cbep497-6-11 - Johnny Hates Jazz - Shattered Dreams\n12. Cbep497-6-12 - Soul Ii Soul - Back To Life (However Do You Want Me)\n13. Cbep497-6-13 - Jones, Howard - Everlasting Love\n14. Cbep497-6-14 - Love &amp; Rockets - So Alive\n15. Cbep497-6-15 - Brickell, Edie &amp; The New Bohemians - What I Am\n16. Cbep497-6-16 - Pretty Poison - Catch Me I'm Falling","torrent":{"xt":"urn:btih:d1007387b288047db9bf72aac78aab67dc6038c0","amp;dn":"Chartbuster+Essential+Plus+Karaoke+CBEP497+-+KaraokeRG","amp;tr":["udp%3A%2F%2Ftracker.openbittorrent.com%3A80","udp%3A%2F%2Fopen.demonii.com%3A1337","udp%3A%2F%2Ftracker.coppersurfer.tk%3A6969","udp%3A%2F%2Fexodus.desync.com%3A6969"],"infoHash":"d1007387b288047db9bf72aac78aab67dc6038c0","infoHashBuffer":{"type":"Buffer","data":[209,0,115,135,178,136,4,125,185,191,114,170,199,138,171,103,220,96,56,192]},"announce":[],"urlList":[]}}