{"title":"Pretty Spanish teen Natty Mellow riding cock","uid":15552865,"size":240239935,"categoryP":"porn","categoryS":"movie_clips","magnet":"?xt=urn:btih:d797d859f9659c523b0ad3c280e7dfd731314913&amp;dn=Pretty+Spanish+teen+Natty+Mellow+riding+cock+PIR%40TE&amp;tr=udp%3A%2F%2Ftracker.leechers-paradise.org%3A6969&amp;tr=udp%3A%2F%2Fzer0day.ch%3A1337&amp;tr=udp%3A%2F%2Fopen.demonii.com%3A1337&amp;tr=udp%3A%2F%2Ftracker.coppersurfer.tk%3A6969&amp;tr=udp%3A%2F%2Fexodus.desync.com%3A6969","seeders":1,"leechers":0,"uploader":"Piratepr0n","files":1,"time":1471041643,"description":"-------------------------------------------------------------------------------------\nName:\nPretty Spanish teen Natty Mellow riding cock   \n  --------------------\nFile list:\nPretty Spanish teen Natty Mellow riding cock    (229 MiB | 1920x1080 | 8min 0s | MPEG-4) \nhttp://imgfapper.com/img-57ae345eb6794.html","torrent":{"xt":"urn:btih:d797d859f9659c523b0ad3c280e7dfd731314913","amp;dn":"Pretty+Spanish+teen+Natty+Mellow+riding+cock+PIR%40TE","amp;tr":["udp%3A%2F%2Ftracker.leechers-paradise.org%3A6969","udp%3A%2F%2Fzer0day.ch%3A1337","udp%3A%2F%2Fopen.demonii.com%3A1337","udp%3A%2F%2Ftracker.coppersurfer.tk%3A6969","udp%3A%2F%2Fexodus.desync.com%3A6969"],"infoHash":"d797d859f9659c523b0ad3c280e7dfd731314913","infoHashBuffer":{"type":"Buffer","data":[215,151,216,89,249,101,156,82,59,10,211,194,128,231,223,215,49,49,73,19]},"announce":[],"urlList":[]}}