{"title":"Elvis Presley - Pearl Harbor show 1961 (1990)","uid":5167450,"size":42596218,"categoryP":"audio","categoryS":"music","magnet":"?xt=urn:btih:d96938202781c96cee78a58bb17c3a6e0aca9820&amp;dn=Elvis+Presley+-+Pearl+Harbor+show+1961+%281990%29&amp;tr=udp%3A%2F%2Ftracker.openbittorrent.com%3A80&amp;tr=udp%3A%2F%2Fopen.demonii.com%3A1337&amp;tr=udp%3A%2F%2Ftracker.coppersurfer.tk%3A6969&amp;tr=udp%3A%2F%2Fexodus.desync.com%3A6969","seeders":1,"leechers":1,"uploader":"Hounddog","files":20,"time":1258488186,"description":"1961 25 march Pearl Harbor show from Elvis. Audience recording Label: Golden Archives.With covers. Enjoy!","torrent":{"xt":"urn:btih:d96938202781c96cee78a58bb17c3a6e0aca9820","amp;dn":"Elvis+Presley+-+Pearl+Harbor+show+1961+%281990%29","amp;tr":["udp%3A%2F%2Ftracker.openbittorrent.com%3A80","udp%3A%2F%2Fopen.demonii.com%3A1337","udp%3A%2F%2Ftracker.coppersurfer.tk%3A6969","udp%3A%2F%2Fexodus.desync.com%3A6969"],"infoHash":"d96938202781c96cee78a58bb17c3a6e0aca9820","infoHashBuffer":{"type":"Buffer","data":[217,105,56,32,39,129,201,108,238,120,165,139,177,124,58,110,10,202,152,32]},"announce":[],"urlList":[]}}