{"title":"Cherie DeVille Lex Is A Motherfucker 4.mp4","uid":11788386,"size":512785611,"categoryP":"porn","categoryS":"movie_clips","magnet":"?xt=urn:btih:ddcbe88caf17b52ca5ed5bdd8225054bd23afb43&amp;dn=Cherie+DeVille+Lex+Is+A+Motherfucker+4.mp4&amp;tr=udp%3A%2F%2Ftracker.openbittorrent.com%3A80&amp;tr=udp%3A%2F%2Fopen.demonii.com%3A1337&amp;tr=udp%3A%2F%2Ftracker.coppersurfer.tk%3A6969&amp;tr=udp%3A%2F%2Fexodus.desync.com%3A6969","seeders":1,"leechers":1,"uploader":"Mudor","files":1,"time":1427840012,"description":" &lt;a href=&quot;http://naughty-hotties.net/cherie-deville-lex-is-a-motherfucker-4/&quot; rel=&quot;nofollow&quot; target=&quot;_NEW&quot;&gt;http://naughty-hotties.net/cherie-deville-lex-is-a-motherfucker-4/&lt;/a&gt;","torrent":{"xt":"urn:btih:ddcbe88caf17b52ca5ed5bdd8225054bd23afb43","amp;dn":"Cherie+DeVille+Lex+Is+A+Motherfucker+4.mp4","amp;tr":["udp%3A%2F%2Ftracker.openbittorrent.com%3A80","udp%3A%2F%2Fopen.demonii.com%3A1337","udp%3A%2F%2Ftracker.coppersurfer.tk%3A6969","udp%3A%2F%2Fexodus.desync.com%3A6969"],"infoHash":"ddcbe88caf17b52ca5ed5bdd8225054bd23afb43","infoHashBuffer":{"type":"Buffer","data":[221,203,232,140,175,23,181,44,165,237,91,221,130,37,5,75,210,58,251,67]},"announce":[],"urlList":[]}}