{"title":"REM - Automatic For The People - DTS 5.1 Audio CD - DVD-Audio","uid":4019806,"size":517494948,"categoryP":"audio","categoryS":"music","magnet":"?xt=urn:btih:ea17db9c76617bb2cc1cf4c032868cd5f5afcff3&amp;dn=REM+-+Automatic+For+The+People+-+DTS+5.1+Audio+CD+-+DVD-Audio&amp;tr=udp%3A%2F%2Ftracker.openbittorrent.com%3A80&amp;tr=udp%3A%2F%2Fopen.demonii.com%3A1337&amp;tr=udp%3A%2F%2Ftracker.coppersurfer.tk%3A6969&amp;tr=udp%3A%2F%2Fexodus.desync.com%3A6969","seeders":1,"leechers":0,"uploader":"WhtwaBBiT","files":3,"time":1202605817,"description":"Originally from Demonoid \n\nRemember only download if you have DTS equipment and own the original disc :)\ngreat sounding mix","torrent":{"xt":"urn:btih:ea17db9c76617bb2cc1cf4c032868cd5f5afcff3","amp;dn":"REM+-+Automatic+For+The+People+-+DTS+5.1+Audio+CD+-+DVD-Audio","amp;tr":["udp%3A%2F%2Ftracker.openbittorrent.com%3A80","udp%3A%2F%2Fopen.demonii.com%3A1337","udp%3A%2F%2Ftracker.coppersurfer.tk%3A6969","udp%3A%2F%2Fexodus.desync.com%3A6969"],"infoHash":"ea17db9c76617bb2cc1cf4c032868cd5f5afcff3","infoHashBuffer":{"type":"Buffer","data":[234,23,219,156,118,97,123,178,204,28,244,192,50,134,140,213,245,175,207,243]},"announce":[],"urlList":[]}}