{"title":"Boomerang [1986] - sum1_here ","uid":9194335,"size":89680774,"categoryP":"audio","categoryS":"other","magnet":"?xt=urn:btih:f02ccc1a4d13fa486be2a2b12b14b21e22801546&amp;dn=Boomerang+%5B1986%5D+-+sum1_here+&amp;tr=udp%3A%2F%2Ftracker.openbittorrent.com%3A80&amp;tr=udp%3A%2F%2Fopen.demonii.com%3A1337&amp;tr=udp%3A%2F%2Ftracker.coppersurfer.tk%3A6969&amp;tr=udp%3A%2F%2Fexodus.desync.com%3A6969","seeders":1,"leechers":0,"uploader":"sum1_here","files":-1,"time":1384453548,"description":":General:\nComplete name: Boomerang [1986] - sum1_here\nFormat: MPEG Audio\nSize: 85.5 MB\nLanguage: English\nUploader: sum1_here\nSource: Thanks\n\n\n\n:Audio:\nFormat: MPEG Audio\nNominal Bitrate: 320 Kbps\nChannel(s): 2 channels\nSampling rate: 44.1 KHz\n","torrent":{"xt":"urn:btih:f02ccc1a4d13fa486be2a2b12b14b21e22801546","amp;dn":"Boomerang+%5B1986%5D+-+sum1_here+","amp;tr":["udp%3A%2F%2Ftracker.openbittorrent.com%3A80","udp%3A%2F%2Fopen.demonii.com%3A1337","udp%3A%2F%2Ftracker.coppersurfer.tk%3A6969","udp%3A%2F%2Fexodus.desync.com%3A6969"],"infoHash":"f02ccc1a4d13fa486be2a2b12b14b21e22801546","infoHashBuffer":{"type":"Buffer","data":[240,44,204,26,77,19,250,72,107,226,162,177,43,20,178,30,34,128,21,70]},"announce":[],"urlList":[]}}